<?xml version="1.0" encoding="UTF-8"?>
<?xml-model href="../../dickinson_schema.rnc" type="application/relax-ng-compact-syntax"?>

<poem>
    <metadata>
        <title>Shall I take thee, the Poet said</title>
        <date>1868</date>
        <source>https://www.edickinson.org/editions/2/image_sets/12171681</source>
        <recipient>none</recipient>
    </metadata>
    
    <body>
        <stanza> 
            <line>Shall I take thee, the Poet said</line>
            <line>To the propounded word?</line>
            <line>Be stationed with the Candidates</line>
            <line>Till I have  vainer  further finer tried -</line>
        </stanza>
        
        <stanza> 
            <line>The Poet  probed searched Philology</line>
            <line>And  when  just was about to ring</line>
            <line>for the suspended Candidate</line>
            <line>Advanced There came unsummoned in -</line>
        </stanza>
        
        <stanza> 
            <line>That portion of the Vision</line>
            <line>The Word applied to fill</line>
            <line>Not unto nomination</line>
            <line>The Cherubim reveal -</line> 
        </stanza>
    </body>
</poem>
